rdconfig/__init__.py
rdconfig/config.py
rdcrm/__init__.py
rdcrm/customer.py
rdcrm/login.py
rdcrm/product.py
rdcrm/salesOrder.py
rdcrm/bill/__init__.py
rdcrm/bill/salesOrder.py
rdcrm/md/__init__.py
rdcrm/md/customer.py
rdcrm/md/product.py
rdoss/__config__.py
rdoss/__init__.py
rdoss/_config_.py
rdoss/main.py
rdoss/rds.py
rdoss-2.4.2.dist-info/LICENSE
rdoss-2.4.2.dist-info/METADATA
rdoss-2.4.2.dist-info/WHEEL
rdoss-2.4.2.dist-info/top_level.txt
rdoss-2.4.2.dist-info/RECORD
