Metadata-Version: 2.1
Name: rdoss
Version: 2.4.2
Summary: object storage for RDS
Home-page: http://www.reshapedata.com
Author: hulilei
Author-email: hulilei@takewiki.com.cn
License: Apache License
Keywords: reshapedata,rdoss
Platform: UNKNOWN
Requires-Python: >=3.6
License-File: LICENSE
Requires-Dist: requests
